pbay/__init__.py
py_pbay-1.0.0.dist-info/METADATA
py_pbay-1.0.0.dist-info/WHEEL
py_pbay-1.0.0.dist-info/top_level.txt
py_pbay-1.0.0.dist-info/RECORD
