Metadata-Version: 2.1
Name: py-pbay
Version: 1.0.0
Summary: A python driver for PBay board
Home-page: https://github.com/tomek-l/py-pbay
Author: Tomasz Lewicki
Author-email: t.w.lewicki@gmail.com
License: UNKNOWN
Platform: UNKNOWN
Classifier: Programming Language :: Python :: 3
Classifier: License :: OSI Approved :: MIT License
Classifier: Operating System :: OS Independent
Requires-Python: >=3.4
